livestock/__init__.py
livestock/air.py
livestock/blender.py
livestock/flow.py
livestock/geometry.py
livestock/hydrology.py
livestock/log.py
livestock/misc.py
livestock/ssh.py
livestock/test/__init__.py
livestock/test/helper_functions.py
livestock/test/test/__init__.py
livestock/test/test/test_air.py
livestock/test/test/test_air_2.py
livestock/test/test/test_boundary_conditions.py
livestock/test/test/test_inlet.py
livestock/test/test/test_model_slope.py
livestock/test/test/test_outlet.py
livestock/test/test/test_weather.py
livestock-2018.9.2.dist-info/METADATA
livestock-2018.9.2.dist-info/RECORD
livestock-2018.9.2.dist-info/WHEEL
livestock-2018.9.2.dist-info/top_level.txt
