Metadata-Version: 2.1
Name: livestock
Version: 2018.9.2
Summary: Livestock is a plugin/library for Grasshopper written in Python
Home-page: https://github.com/ocni-dtu/livestock
Author: Christian Kongsgaard
Author-email: ocni@dtu.dk
License: GNU GPLv3
Requires-Dist: scipy
Requires-Dist: numpy
Requires-Dist: paramiko
Requires-Dist: pyshp
Requires-Dist: shapely
Requires-Dist: cmf (==1.2)
Requires-Dist: xmltodict
Requires-Dist: dbfread
Requires-Dist: progressbar2
